lidar_camera_calibration/__init__.py
lidar_camera_calibration/__main__.py
lidar_camera_calibration/tools/__init__.py
lidar_camera_calibration/tools/calibration.py
lidar_camera_calibration/tools/dataset.py
lidar_camera_calibration/tools/fmin.py
lidar_camera_calibration/tools/general.py
lidar_camera_calibration/tools/image.py
lidar_camera_calibration/tools/model.py
lidar_camera_calibration/tools/plot.py
lidar_camera_calibration/tools/point_cloud2.py
lidar_camera_calibration/tools/rosbag.py
lidar_camera_calibration/tools/rotations.py
lidar_camera_calibration/tools/setup.py
lidar_camera_calibration/tools/timestamp_np.py
lidar_camera_calibration-0.0.15.dist-info/METADATA
lidar_camera_calibration-0.0.15.dist-info/WHEEL
lidar_camera_calibration-0.0.15.dist-info/entry_points.txt
lidar_camera_calibration-0.0.15.dist-info/top_level.txt
lidar_camera_calibration-0.0.15.dist-info/RECORD
