Metadata-Version: 2.1
Name: lidar-camera-calibration
Version: 0.0.15
Summary: LiDAR camera calibration
Home-page: https://github.com/kiakahabro/lidar-camera-calibration
Author: Timothy Farnworth
Author-email: tkfarnworth@gmail.com
Keywords: python,calibration,LiDAR,camera
Classifier: Development Status :: 3 - Alpha
Classifier: Intended Audience :: Science/Research
Classifier: Programming Language :: Python :: 3
Classifier: Operating System :: MacOS :: MacOS X
Classifier: Operating System :: POSIX :: Linux
Requires-Dist: matplotlib
Requires-Dist: pathlib2
Requires-Dist: pyqt5
Requires-Dist: pyyaml
Requires-Dist: scikit-learn
Requires-Dist: scipy
Requires-Dist: torch
Requires-Dist: typer[all]
Requires-Dist: rosbags
Requires-Dist: natsort
